pytblis/__init__.py
pytblis/_pytblis_impl.cpython-311-aarch64-linux-gnu.so
pytblis/_pytblis_impl.pyi
pytblis/einsum_impl.py
pytblis/mixedtype.py
pytblis/tensordot_impl.py
pytblis/typecheck.py
pytblis/wrappers.py
pytblis.libs/libhwloc-8ede5728.so.15.2.0
pytblis.libs/libtblis-1f4b5a03.so
pytblis-0.0.12.dist-info/METADATA
pytblis-0.0.12.dist-info/WHEEL
pytblis-0.0.12.dist-info/RECORD
pytblis-0.0.12.dist-info/licenses/LICENSE
pytblis-0.0.12.dist-info/sboms/auditwheel.cdx.json
