Metadata-Version: 2.4
Name: pytblis
Version: 0.0.12
Summary: Python bindings for TBLIS, a high performance library for tensor operations
Author-Email: Christopher Hillenbrand <chillenbrand15@gmail.com>
License-Expression: BSD-3-Clause
License-File: LICENSE
Classifier: Development Status :: 1 - Planning
Classifier: Intended Audience :: Science/Research
Classifier: Intended Audience :: Developers
Classifier: Operating System :: OS Independent
Classifier: Programming Language :: Python
Classifier: Programming Language :: Python :: 3
Classifier: Programming Language :: Python :: 3 :: Only
Classifier: Programming Language :: Python :: 3.9
Classifier: Programming Language :: Python :: 3.10
Classifier: Programming Language :: Python :: 3.11
Classifier: Programming Language :: Python :: 3.12
Classifier: Programming Language :: Python :: 3.13
Classifier: Topic :: Scientific/Engineering
Classifier: Typing :: Typed
Project-URL: Homepage, https://github.com/chillenb/pytblis
Project-URL: Bug Tracker, https://github.com/chillenb/pytblis/issues
Project-URL: Discussions, https://github.com/chillenb/pytblis/discussions
Project-URL: Changelog, https://github.com/chillenb/pytblis/releases
Project-URL: Documentation, https://pytblis.readthedocs.io
Requires-Python: >=3.9
Requires-Dist: numpy
Provides-Extra: tests
Requires-Dist: pytest>=6; extra == "tests"
Requires-Dist: pytest-cov>=3; extra == "tests"
